README.rst
setup.cfg
setup.py
vnpy_akshare/__init__.py
vnpy_akshare/akshre_feed.py
vnpy_akshare/utils/__init__.py
vnpy_akshare/utils/dask_utils.py
vnpy_akshare/utils/date_utils.py
vnpy_akshare/utils/execpt.py
vnpy_akshare/utils/log.py
vnpy_akshare/utils/misc.py
vnpy_akshare/utils/thread_util.py
vnpy_askshare.egg-info/PKG-INFO
vnpy_askshare.egg-info/SOURCES.txt
vnpy_askshare.egg-info/dependency_links.txt
vnpy_askshare.egg-info/not-zip-safe
vnpy_askshare.egg-info/requires.txt
vnpy_askshare.egg-info/top_level.txt